[
  {
    "first_name": "Devon",
    "last_name": "Nye",
    "dob": null,
    "anniversary": null,
    "email": null,
    "phone_number": null,
    "address": {
      "line1": null,
      "line2": null,
      "city": null,
      "state": null,
      "country": null,
      "postal_code": null
    }
  },
  {
    "first_name": "David",
    "last_name": "Copperfield",
    "dob": null,
    "anniversary": null,
    "email": null,
    "phone_number": null,
    "address": {
      "line1": null,
      "line2": null,
      "city": null,
      "state": null,
      "country": null,
      "postal_code": null
    }
  },
  {
    "first_name": "James",
    "last_name": "Bond",
    "dob": null,
    "anniversary": null,
    "email": null,
    "phone_number": null,
    "address": {
      "line1": null,
      "line2": null,
      "city": null,
      "state": null,
      "country": null,
      "postal_code": null
    }
  }
]
